pyamplipi/__init__.py
pyamplipi/__main__.py
pyamplipi/amplipi.py
pyamplipi/client.py
pyamplipi/error.py
pyamplipi/example.py
pyamplipi/models.py
pyamplipi-0.4.12.dist-info/LICENSE
pyamplipi-0.4.12.dist-info/METADATA
pyamplipi-0.4.12.dist-info/WHEEL
pyamplipi-0.4.12.dist-info/entry_points.txt
pyamplipi-0.4.12.dist-info/top_level.txt
pyamplipi-0.4.12.dist-info/zip-safe
pyamplipi-0.4.12.dist-info/RECORD
